RepoAuditor/CommandLineProcessor.py
RepoAuditor/Display.py
RepoAuditor/EntryPoint.py
RepoAuditor/ExecuteModules.py
RepoAuditor/Module.py
RepoAuditor/Plugin.py
RepoAuditor/Query.py
RepoAuditor/Requirement.py
RepoAuditor/__init__.py
RepoAuditor/py.typed
RepoAuditor/Impl/ParallelSequentialProcessor.py
RepoAuditor/Impl/__init__.py
RepoAuditor/Plugins/CommunityStandardsPlugin.py
RepoAuditor/Plugins/GitHubPlugin.py
RepoAuditor/Plugins/ScientificSoftwarePlugin.py
RepoAuditor/Plugins/__init__.py
RepoAuditor/Plugins/CommunityStandards/CommunityStandardsQuery.py
RepoAuditor/Plugins/CommunityStandards/Module.py
RepoAuditor/Plugins/CommunityStandards/__init__.py
RepoAuditor/Plugins/CommunityStandards/Impl/ExistsRequirementImpl.py
RepoAuditor/Plugins/CommunityStandards/Impl/__init__.py
RepoAuditor/Plugins/CommunityStandards/Requirements/CodeOfConduct.py
RepoAuditor/Plugins/CommunityStandards/Requirements/CodeOwners.py
RepoAuditor/Plugins/CommunityStandards/Requirements/Contributing.py
RepoAuditor/Plugins/CommunityStandards/Requirements/IssueTemplates.py
RepoAuditor/Plugins/CommunityStandards/Requirements/LicenseFile.py
RepoAuditor/Plugins/CommunityStandards/Requirements/PullRequestTemplates.py
RepoAuditor/Plugins/CommunityStandards/Requirements/ReadMe.py
RepoAuditor/Plugins/CommunityStandards/Requirements/SecurityPolicy.py
RepoAuditor/Plugins/CommunityStandards/Requirements/__init__.py
RepoAuditor/Plugins/GitHub/ClassicBranchProtectionQuery.py
RepoAuditor/Plugins/GitHub/DefaultBranchQuery.py
RepoAuditor/Plugins/GitHub/Module.py
RepoAuditor/Plugins/GitHub/RulesetQuery.py
RepoAuditor/Plugins/GitHub/StandardQuery.py
RepoAuditor/Plugins/GitHub/__init__.py
RepoAuditor/Plugins/GitHub/ClassicBranchProtectionRequirements/AllowDeletions.py
RepoAuditor/Plugins/GitHub/ClassicBranchProtectionRequirements/AllowMainlineForcePushes.py
RepoAuditor/Plugins/GitHub/ClassicBranchProtectionRequirements/DismissStalePullRequestApprovals.py
repoauditor-0.4.6.dist-info/METADATA
repoauditor-0.4.6.dist-info/WHEEL
repoauditor-0.4.6.dist-info/entry_points.txt
repoauditor-0.4.6.dist-info/licenses/LICENSE
repoauditor-0.4.6.dist-info/RECORD
