Metadata-Version: 2.4
Name: RepoAuditor
Version: 0.4.6
Summary: Add your description here
Project-URL: Homepage, https://github.com/gt-sse-center/RepoAuditor
Project-URL: Documentation, https://github.com/gt-sse-center/RepoAuditor
Project-URL: Repository, https://github.com/gt-sse-center/RepoAuditor
Author-email: Scientific Software Engineering Center at Georgia Tech <sse-center@gatech.edu>
License: MIT
License-File: LICENSE
Classifier: Operating System :: MacOS
Classifier: Operating System :: Microsoft :: Windows
Classifier: Operating System :: POSIX :: Linux
Classifier: Programming Language :: Python
Classifier: Programming Language :: Python :: 3.10
Classifier: Programming Language :: Python :: 3.11
Classifier: Programming Language :: Python :: 3.12
Classifier: Programming Language :: Python :: 3.13
Requires-Python: >=3.10
Requires-Dist: dbrownell-common>=0.16.0
Requires-Dist: gitpython>=3.1.44
Requires-Dist: pluggy>=1.5.0
Requires-Dist: requests>=2.32.3
Requires-Dist: typer-config[yaml]>=1.4.2
Requires-Dist: typer>=0.15.3
